{
  "project_info": {
    "project_number": "591673871843",
    "firebase_url": "https://chalo-a910a.firebaseio.com",
    "project_id": "chalo-a910a",
    "storage_bucket": "chalo-a910a.appspot.com"
  },
  "client": [
    {
      "client_info": {
        "mobilesdk_app_id": "1:591673871843:android:adbc640636d89467d224d6",
        "android_client_info": {
          "package_name": "com.northstarinnovations.chalo"
        }
      },
      "oauth_client": [
        {
          "client_id": "591673871843-c1a25hbar5o1trn0clvuoda70ogqds5t.apps.googleusercontent.com",
          "client_type": 1,
          "android_info": {
            "package_name": "com.northstarinnovations.chalo",
            "certificate_hash": "ffd246f0ee188f7965d23a0fef9dc8d37c58f5fd"
          }
        },
        {
          "client_id": "591673871843-o4bln0sqsi18kuj46uh6bbri0b9l3qmd.apps.googleusercontent.com",
          "client_type": 1,
          "android_info": {
            "package_name": "com.northstarinnovations.chalo",
            "certificate_hash": "f48e3a8978dfc0a36eddaf5e264883be1c9fdc31"
          }
        },
        {
          "client_id": "591673871843-9anbtlpgidhl37t6rcps32n02cd67mob.apps.googleusercontent.com",
          "client_type": 3
        }
      ],
      "api_key": [
        {
          "current_key": "AIzaSyBz9fvvLqZH3xTxuQ9lIZabfGTe_Br6i3Q"
        }
      ],
      "services": {
        "appinvite_service": {
          "other_platform_oauth_client": [
            {
              "client_id": "591673871843-9anbtlpgidhl37t6rcps32n02cd67mob.apps.googleusercontent.com",
              "client_type": 3
            },
            {
              "client_id": "591673871843-25t6cccst0lli90sc7cclu2a5j8p38q9.apps.googleusercontent.com",
              "client_type": 2,
              "ios_info": {
                "bundle_id": "com.northstarinnovations.chalo"
              }
            }
          ]
        }
      }
    }
  ],
  "configuration_version": "1"
}